beatboxer/__init__.py
beatboxer/beatboxer.py
beatboxer/gui.py
beatboxer/icon/icon.ico
beatboxer/samples/bass.wav
beatboxer/samples/clap.wav
beatboxer/samples/crash.wav
beatboxer/samples/hihat.wav
beatboxer/samples/kick.wav
beatboxer/samples/snare.wav
beatboxer-2.0.2.dist-info/METADATA
beatboxer-2.0.2.dist-info/RECORD
beatboxer-2.0.2.dist-info/WHEEL
beatboxer-2.0.2.dist-info/top_level.txt
