Metadata-Version: 2.1
Name: beatboxer
Version: 2.0.2
Summary: A beatboxer to create custom beats.
Home-page: https://github.com/crumpstrr33/beatboxer
Author: Jacob Scott
Author-email: jscott12009@gmail.com
License: MIT
Platform: UNKNOWN
Classifier: Intended Audience :: End Users/Desktop
Classifier: License :: OSI Approved :: MIT License
Classifier: Programming Language :: Python :: 3 :: Only
Requires-Python: >=3
Requires-Dist: pydub
